OpenHub/__init__.py
OpenHub/__main__.py
OpenHub/calibrate.py
OpenHub/characteristics.json
OpenHub/config_files.py
OpenHub/garden_bridge.py
OpenHub/globals.py
OpenHub/ip_resolver.py
OpenHub/run_bridge.py
OpenHub/services.json
OpenHub/soil_sensor.json
OpenHub/utilities.py
OpenHub/camera/__init__.py
OpenHub/camera/camera.py
OpenHub/config/__init__.py
OpenHub/config/reader.py
OpenHub/config/writer.py
OpenHub/data_transformers/__init__.py
OpenHub/data_transformers/data_transformer.py
OpenHub/data_transformers/difference.py
OpenHub/data_transformers/divide.py
OpenHub/data_transformers/inverse.py
OpenHub/data_transformers/max.py
OpenHub/data_transformers/min.py
OpenHub/data_transformers/product.py
OpenHub/data_transformers/sum.py
OpenHub/data_transformers/constants/__init__.py
OpenHub/data_transformers/constants/constant.py
OpenHub/data_transformers/json/__init__.py
OpenHub/data_transformers/json/data_transformer_decoder.py
OpenHub/hardware_interfaces/PMSA0031.py
OpenHub/hardware_interfaces/__init__.py
OpenHub/hardware_interfaces/adafruit_stepper_motor_hat.py
OpenHub/hardware_interfaces/am2315.py
OpenHub/hardware_interfaces/dht22.py
OpenHub/hardware_interfaces/hardware_interface.py
OpenHub/hardware_interfaces/mcp3008.py
OpenHub/hardware_interfaces/mod_probe.py
OpenHub/hardware_interfaces/pi.py
OpenHub/hardware_interfaces/pi_pico.py
OpenHub/hardware_interfaces/veml_7700.py
OpenHub/hardware_interfaces/base_io/__init__.py
OpenHub/hardware_interfaces/base_io/base_io_interface.py
OpenHub/hardware_interfaces/base_io/device_file_io.py
OpenHub/hardware_interfaces/base_io/i2c.py
OpenHub/hardware_interfaces/base_io/mcp_analog_io.py
OpenHub/hardware_interfaces/base_io/pi_digital_io.py
OpenHub/hardware_interfaces/base_io/pi_gpi.py
OpenHub/hardware_interfaces/base_io/pi_gpo.py
OpenHub/hardware_interfaces/base_io/pi_pico_analog_io.py
OpenHub/hardware_interfaces/base_io/pi_pico_gpi.py
OpenHub/hardware_interfaces/base_io/pi_pico_gpo.py
OpenHub/hardware_interfaces/base_io/pi_pico_pwm.py
openhub-0.0.204.dist-info/LICENSE
openhub-0.0.204.dist-info/METADATA
openhub-0.0.204.dist-info/WHEEL
openhub-0.0.204.dist-info/top_level.txt
openhub-0.0.204.dist-info/RECORD
