Metadata-Version: 2.1
Name: openhub
Version: 0.0.204
Summary: An open source iOT controller.
Home-page: https://github.com/ganonp/GardenHub
Author: Ganon Pierce
Author-email: ganonp@gmail.com
License: UNKNOWN
Platform: UNKNOWN
Requires-Python: >=3.6
License-File: LICENSE
Requires-Dist: markdown
Requires-Dist: pigpio-dht
Requires-Dist: adafruit-circuitpython-motorkit
Requires-Dist: adafruit-circuitpython-am2320
Requires-Dist: adafruit-circuitpython-dht
Requires-Dist: adafruit-circuitpython-pm25
Requires-Dist: Adafruit-Blinka (==6.10.1)
Requires-Dist: adafruit-circuitpython-busdevice (==5.0.6)
Requires-Dist: adafruit-circuitpython-mcp3xxx (==1.4.5)
Requires-Dist: adafruit-circuitpython-register (==1.9.5)
Requires-Dist: adafruit-circuitpython-veml7700 (==1.1.7)
Requires-Dist: Adafruit-GPIO (==1.0.3)
Requires-Dist: Adafruit-PlatformDetect (>=3.19.3)
Requires-Dist: Adafruit-PureIO (==1.1.8)
Requires-Dist: asgiref (==3.3.4)
Requires-Dist: asn1crypto (==0.24.0)
Requires-Dist: attrs (==21.2.0)
Requires-Dist: autobahn (==21.3.1)
Requires-Dist: Automat (==20.2.0)
Requires-Dist: certifi (==2018.8.24)
Requires-Dist: cffi (==1.14.5)
Requires-Dist: chardet (==3.0.4)
Requires-Dist: constantly (==15.1.0)
Requires-Dist: cryptography (==3.4.7)
Requires-Dist: curve25519-donna (==1.3)
Requires-Dist: daphne (==3.0.2)
Requires-Dist: ed25519 (==1.5)
Requires-Dist: entrypoints (==0.3)
Requires-Dist: h11 (==0.12.0)
Requires-Dist: HAP-python[qrcode]
Requires-Dist: hyperlink (==21.0.0)
Requires-Dist: idna (==2.6)
Requires-Dist: ifaddr (==0.1.7)
Requires-Dist: incremental (==21.3.0)
Requires-Dist: keyring (==17.1.1)
Requires-Dist: keyrings.alt (==3.1.1)
Requires-Dist: paho-mqtt (==1.5.1)
Requires-Dist: pyasn1 (==0.4.8)
Requires-Dist: pyasn1-modules (==0.2.8)
Requires-Dist: pycparser (==2.20)
Requires-Dist: pycrypto (==2.6.1)
Requires-Dist: pyftdi (==0.53.1)
Requires-Dist: pyOpenSSL (==20.0.1)
Requires-Dist: pyserial (==3.5)
Requires-Dist: pytz (==2021.1)
Requires-Dist: pyxdg (==0.25)
Requires-Dist: requests (==2.21.0)
Requires-Dist: SecretStorage (==2.3.1)
Requires-Dist: service-identity (==21.1.0)
Requires-Dist: six (==1.12.0)
Requires-Dist: sqlparse (==0.4.1)
Requires-Dist: ssh-import-id
Requires-Dist: sysv-ipc (==1.1.0)
Requires-Dist: Twisted (==21.2.0)
Requires-Dist: txaio (==21.2.1)
Requires-Dist: typing-extensions (==3.10.0.0)
Requires-Dist: urllib3 (==1.24.1)
Requires-Dist: websockets (==9.1)
Requires-Dist: zeroconf (==0.31.0)
Requires-Dist: zope.interface (==5.4.0)
Requires-Dist: RPi.GPIO
Requires-Dist: RPi.Sensor
